dotpop/__init__.py
dotpop/cli.py
dotpop/conditions.py
dotpop/crypto.py
dotpop/exceptions.py
dotpop/helpers.py
dotpop/loader.py
dotpop/parser.py
dotpop/resolved_env.py
dotpop/resolver.py
dotpop/types.py
dotpop/validators.py
dotpop-1.0.1.dist-info/licenses/LICENSE
dotpop-1.0.1.dist-info/METADATA
dotpop-1.0.1.dist-info/WHEEL
dotpop-1.0.1.dist-info/top_level.txt
dotpop-1.0.1.dist-info/RECORD
